ezformer/__init__.py
ezformer/models.py
ezformer/predict.py
ezformer/process.py
ezformer/utils.py
pyproject.toml
ezformer-0.0.2.dist-info/LICENSE
ezformer-0.0.2.dist-info/METADATA
ezformer-0.0.2.dist-info/WHEEL
ezformer-0.0.2.dist-info/RECORD
