Metadata-Version: 2.1
Name: ezformer
Version: 0.0.2
Summary: Run enformer like models, get prediction tracks, and perform benchmarking
License: MIT
Author: Abe Arab
Author-email: abarbiology@gmail.com
Requires-Python: >=3.9,<4.0
Classifier: License :: OSI Approved :: MIT License
Classifier: Programming Language :: Python :: 3
Classifier: Programming Language :: Python :: 3.9
Classifier: Programming Language :: Python :: 3.10
Classifier: Programming Language :: Python :: 3.11
Classifier: Programming Language :: Python :: 3.12
Classifier: Programming Language :: Python :: 3.13
Requires-Dist: anndata
Requires-Dist: gReLU
Requires-Dist: kipoiseq
Requires-Dist: lightning
Requires-Dist: numpy
Requires-Dist: pandas
Requires-Dist: tangermeme
Requires-Dist: tensorflow
Requires-Dist: tensorflow_hub
Project-URL: Source, https://github.com/abearab/ezformer
